AMAT/__init__.py
AMAT/approach.py
AMAT/interplanetary.py
AMAT/launcher.py
AMAT/maneuver.py
AMAT/orbiter.py
AMAT/planet.py
AMAT/telecom.py
AMAT/vehicle.py
AMAT/visibility.py
AMAT-2.3.0.dist-info/LICENSE
AMAT-2.3.0.dist-info/METADATA
AMAT-2.3.0.dist-info/WHEEL
AMAT-2.3.0.dist-info/top_level.txt
AMAT-2.3.0.dist-info/RECORD
