Metadata-Version: 2.1
Name: AMAT
Version: 2.3.0
Summary: Aerocapture Mission Analysis Tool
Home-page: https://github.com/athulpg007/AMAT
Author: Athul P. Girija
Author-email: athulpg007@gmail.com
License: GPL-3.0-or-later
Classifier: Development Status :: 5 - Production/Stable
Classifier: Intended Audience :: Developers
Classifier: Intended Audience :: Science/Research
Classifier: Intended Audience :: Education
Classifier: Topic :: Scientific/Engineering
Classifier: Topic :: Scientific/Engineering :: Mathematics
Classifier: Topic :: Scientific/Engineering :: Physics
Classifier: Programming Language :: Python :: 3.10
Classifier: Programming Language :: Python :: 3.11
Classifier: Programming Language :: Python :: 3.12
License-File: LICENSE
Requires-Dist: numpy ==1.26.2
Requires-Dist: scipy ==1.11.4
Requires-Dist: matplotlib ==3.8.2
Requires-Dist: pandas ==2.1.4
Requires-Dist: astropy ==6.0.0
Requires-Dist: jplephem ==2.21
